genaishap/__init__.py
genaishap/_utils.py
genaishap/explainer.py
genaishap/featurize.py
genaishap/prompts.py
genaishap-0.0.3.dist-info/METADATA
genaishap-0.0.3.dist-info/WHEEL
genaishap-0.0.3.dist-info/licenses/LICENSE
genaishap-0.0.3.dist-info/RECORD
