Metadata-Version: 2.4
Name: genaishap
Version: 0.0.3
Summary: SHAP (SHapley Additive exPlanations) for Generative AI (LLMs and SMLs) based solutions.
Project-URL: Homepage, https://github.com/microsoft/dstoolkit-genai-shap
Project-URL: Issues, https://github.com/microsoft/dstoolkit-genai-shap/issues
Author-email: Gustavo Pabon <gustavo.pabon@microsoft.com>
License-File: LICENSE
Classifier: Development Status :: 2 - Pre-Alpha
Classifier: License :: OSI Approved :: MIT License
Classifier: Operating System :: OS Independent
Classifier: Programming Language :: Python :: 3
Classifier: Topic :: Scientific/Engineering :: Artificial Intelligence
Classifier: Topic :: Software Development :: Debuggers
Requires-Python: >=3.9
Requires-Dist: openai==1.59.7
Requires-Dist: pandas==2.2.3
Requires-Dist: pydantic==2.10.5
Requires-Dist: scikit-learn==1.5.2
Requires-Dist: scipy==1.13.1
Requires-Dist: shap==0.46.0
Requires-Dist: statsmodels==0.14.4
Requires-Dist: xgboost==2.1.3
